COPYING
ChangeLog
MANIFEST.in
NEWS
README
recalc-fingerprints.py
release.py
setup.cfg
setup.py
conf/u2fval.conf
doc/Apache_Deployment.adoc
doc/Database_Setup.adoc
doc/Installation.adoc
doc/Logging.adoc
doc/Metadata_Format.adoc
doc/Migrating_From_Older_Versions.adoc
doc/REST_API.adoc
doc/Using_Memcached.adoc
man/u2fval.1.adoc
test/test_api.py
u2fval/__init__.py
u2fval/cli.py
u2fval/default_settings.py
u2fval/exc.py
u2fval/jsobjects.py
u2fval/model.py
u2fval/transactiondb.py
u2fval/view.py
u2fval.egg-info/PKG-INFO
u2fval.egg-info/SOURCES.txt
u2fval.egg-info/dependency_links.txt
u2fval.egg-info/entry_points.txt
u2fval.egg-info/requires.txt
u2fval.egg-info/top_level.txt
u2fval/core/__init__.py