Metadata-Version: 1.1
Name: u2fval
Version: 2.0.0
Summary: Standalone/WSGI U2F server implementing the U2FVAL protocol
Home-page: https://github.com/Yubico/u2fval
Author: Yubico Open Source Maintainers
Author-email: ossmaint@yubico.com
License: BSD 2 clause
Platform: UNKNOWN
Classifier: License :: OSI Approved :: BSD License
Classifier: Operating System :: OS Independent
Classifier: Development Status :: 4 - Beta
Classifier: Intended Audience :: Developers
Classifier: Intended Audience :: System Administrators
Classifier: Programming Language :: Python :: 2
Classifier: Programming Language :: Python :: 2.7
Classifier: Programming Language :: Python :: 3
Classifier: Programming Language :: Python :: 3.3
Classifier: Programming Language :: Python :: 3.4
Classifier: Programming Language :: Python :: 3.5
Classifier: Programming Language :: Python :: 3.6
Classifier: Programming Language :: Python :: Implementation :: PyPy
Classifier: Topic :: Internet
Classifier: Topic :: Security
Classifier: Topic :: Internet :: WWW/HTTP :: WSGI :: Application
